wagtail_block_exchange/__init__.py
wagtail_block_exchange/apps.py
wagtail_block_exchange/models.py
wagtail_block_exchange/services.py
wagtail_block_exchange/signals.py
wagtail_block_exchange/urls.py
wagtail_block_exchange/views.py
wagtail_block_exchange/wagtail_hooks.py
wagtail_block_exchange/migrations/0001_initial.py
wagtail_block_exchange/migrations/__init__.py
wagtail_block_exchange/static/wagtail_block_exchange/css/block-exchange.css
wagtail_block_exchange/static/wagtail_block_exchange/js/dist/wagtail_block_exchange.js
wagtail_block_exchange/templates/wagtail_block_exchange/clipboard.html
wagtail_block_exchange-0.1.0.data/data/static/wagtail_block_exchange/css/block-exchange.css
wagtail_block_exchange-0.1.0.data/data/static/wagtail_block_exchange/js/dist/wagtail_block_exchange.js
wagtail_block_exchange-0.1.0.dist-info/LICENSE
wagtail_block_exchange-0.1.0.dist-info/METADATA
wagtail_block_exchange-0.1.0.dist-info/WHEEL
wagtail_block_exchange-0.1.0.dist-info/top_level.txt
wagtail_block_exchange-0.1.0.dist-info/RECORD
