Metadata-Version: 2.2
Name: wagtail-block-exchange
Version: 0.1.0
Summary: A Wagtail plugin to copy and paste blocks between pages
Home-page: https://gitlab.com/welovemicro/wagtail-block-exchange
Author: Rich Ross
Author-email: rich@welovemicro.com
Project-URL: Bug Tracker, https://gitlab.com/welovemicro/wagtail-block-exchange/-/issues
Project-URL: Documentation, https://gitlab.com/welovemicro/wagtail-block-exchange/-/blob/main/README.md
Project-URL: Source Code, https://gitlab.com/welovemicro/wagtail-block-exchange
Classifier: Programming Language :: Python :: 3
Classifier: License :: OSI Approved :: MIT License
Classifier: Operating System :: OS Independent
Classifier: Framework :: Django
Classifier: Framework :: Wagtail
Classifier: Framework :: Wagtail :: 4
Classifier: Framework :: Wagtail :: 5
Classifier: Topic :: Software Development :: Libraries :: Python Modules
Classifier: Development Status :: 4 - Beta
Requires-Python: >=3.8
License-File: LICENSE
Requires-Dist: wagtail>=4.1
Requires-Dist: django>=3.2
Dynamic: author
Dynamic: author-email
Dynamic: classifier
Dynamic: description
Dynamic: description-content-type
Dynamic: home-page
Dynamic: project-url
Dynamic: requires-dist
Dynamic: requires-python
Dynamic: summary
